[
    {
        "school": {
            "name": "High Tech High Graduate School of Education",
            "city": "San Diego",
            "state": "CA",
            "zip": "92106",
            "accreditor": "Western Association of Schools and Colleges Senior Colleges and University Commission",
            "school_url": "https://hthgse.edu/",
            "price_calculator_url": "https://hthgse.edu/admissions/funding-financial-aid/",
            "degrees_awarded": {
                "predominant_recoded": null,
                "predominant": 4,
                "highest": 4
            },
            "under_investigation": 0,
            "main_campus": 1,
            "branches": 1,
            "ownership": 2,
            "state_fips": 6,
            "region_id": 8,
            "locale": 11,
            "degree_urbanization": null,
            "carnegie_basic": 32,
            "carnegie_undergrad": 0,
            "carnegie_size_setting": 18,
            "minority_serving": {
                "historically_black": 0,
                "predominantly_black": 0,
                "annh": 0,
                "tribal": 0,
                "aanipi": 0,
                "hispanic": 0,
                "nant": 0
            },
            "men_only": 0,
            "women_only": 0,
            "religious_affiliation": null,
            "online_only": 0,
            "operating": 1,
            "tuition_revenue_per_fte": 14885,
            "instructional_expenditure_per_fte": 106483,
            "faculty_salary": null,
            "ft_faculty_rate": 0.9643,
            "alias": null,
            "institutional_characteristics": {
                "level": 1
            },
            "open_admissions_policy": null,
            "accreditor_code": "WASCSR",
            "title_iv": {
                "approval_date": "6/20/2014",
                "eligibility_type": 1
            },
            "ownership_peps": 2,
            "endowment": {
                "begin": null,
                "end": null
            },
            "dolflag": 0,
            "search": null
        },
        "id": 485403
    },
    {
        "school": {
            "name": "Coachella Valley Beauty College-Hemet",
            "city": "Hemet",
            "state": "CA",
            "zip": "92545",
            "accreditor": "National Accrediting Commission of Career Arts and Sciences",
            "school_url": "cvbeautycollege.com/",
            "price_calculator_url": "www.cvbeautycollege.com/Financial-Aid",
            "degrees_awarded": {
                "predominant_recoded": 1,
                "predominant": 1,
                "highest": 1
            },
            "under_investigation": 0,
            "main_campus": 0,
            "branches": 2,
            "ownership": 3,
            "state_fips": 6,
            "region_id": 8,
            "locale": 22,
            "degree_urbanization": null,
            "carnegie_basic": -2,
            "carnegie_undergrad": -2,
            "carnegie_size_setting": -2,
            "minority_serving": {
                "historically_black": 0,
                "predominantly_black": 0,
                "annh": 0,
                "tribal": 0,
                "aanipi": 0,
                "hispanic": 0,
                "nant": 0
            },
            "men_only": 0,
            "women_only": 0,
            "religious_affiliation": null,
            "online_only": 0,
            "operating": 1,
            "tuition_revenue_per_fte": 9250,
            "instructional_expenditure_per_fte": 1737,
            "faculty_salary": null,
            "ft_faculty_rate": null,
            "alias": "CV Beauty College",
            "institutional_characteristics": {
                "level": 3
            },
            "open_admissions_policy": 1,
            "accreditor_code": "NACCAS",
            "title_iv": {
                "approval_date": "8/27/2013",
                "eligibility_type": 1
            },
            "ownership_peps": 3,
            "endowment": {
                "begin": null,
                "end": null
            },
            "dolflag": 0,
            "search": null
        },
        "id": 485412
    },
    {
        "school": {
            "name": "Coastal Pines Technical College",
            "city": "Waycross",
            "state": "GA",
            "zip": "31503",
            "accreditor": "Southern Association of Colleges and Schools Commission on Colleges",
            "school_url": "www.coastalpines.edu/",
            "price_calculator_url": "www.coastalpines.edu/wysiwyg.aspx?ModuleId=147",
            "degrees_awarded": {
                "predominant_recoded": 1,
                "predominant": 1,
                "highest": 2
            },
            "under_investigation": 0,
            "main_campus": 1,
            "branches": 1,
            "ownership": 1,
            "state_fips": 13,
            "region_id": 5,
            "locale": 33,
            "degree_urbanization": null,
            "carnegie_basic": 9,
            "carnegie_undergrad": 1,
            "carnegie_size_setting": 2,
            "minority_serving": {
                "historically_black": 0,
                "predominantly_black": 0,
                "annh": 0,
                "tribal": 0,
                "aanipi": 0,
                "hispanic": 0,
                "nant": 0
            },
            "men_only": 0,
            "women_only": 0,
            "religious_affiliation": null,
            "online_only": 0,
            "operating": 1,
            "tuition_revenue_per_fte": 2831,
            "instructional_expenditure_per_fte": 4543,
            "faculty_salary": 4052,
            "ft_faculty_rate": 0.6809,
            "alias": null,
            "institutional_characteristics": {
                "level": 2
            },
            "open_admissions_policy": 1,
            "accreditor_code": "SACSCC",
            "title_iv": {
                "approval_date": "11/1/1966",
                "eligibility_type": 1
            },
            "ownership_peps": 1,
            "endowment": {
                "begin": null,
                "end": null
            },
            "dolflag": 1,
            "search": null
        },
        "id": 485458
    },
    {
        "school": {
            "name": "Studio Beauty School",
            "city": "Spokane Valley",
            "state": "WA",
            "zip": "99206",
            "accreditor": "National Accrediting Commission of Career Arts and Sciences",
            "school_url": "www.studiobeautyschool.com/",
            "price_calculator_url": "www.studiobeautyschool.com/admissions-catalog",
            "degrees_awarded": {
                "predominant_recoded": 1,
                "predominant": 1,
                "highest": 1
            },
            "under_investigation": 0,
            "main_campus": 1,
            "branches": 1,
            "ownership": 3,
            "state_fips": 53,
            "region_id": 8,
            "locale": 12,
            "degree_urbanization": null,
            "carnegie_basic": -2,
            "carnegie_undergrad": -2,
            "carnegie_size_setting": -2,
            "minority_serving": {
                "historically_black": 0,
                "predominantly_black": 0,
                "annh": 0,
                "tribal": 0,
                "aanipi": 0,
                "hispanic": 0,
                "nant": 0
            },
            "men_only": 0,
            "women_only": 0,
            "religious_affiliation": null,
            "online_only": 0,
            "operating": 1,
            "tuition_revenue_per_fte": 11316,
            "instructional_expenditure_per_fte": 5309,
            "faculty_salary": null,
            "ft_faculty_rate": null,
            "alias": null,
            "institutional_characteristics": {
                "level": 3
            },
            "open_admissions_policy": 1,
            "accreditor_code": "NACCAS",
            "title_iv": {
                "approval_date": "6/25/2014",
                "eligibility_type": 1
            },
            "ownership_peps": 3,
            "endowment": {
                "begin": null,
                "end": null
            },
            "dolflag": 1,
            "search": null
        },
        "id": 485476
    },
    {
        "school": {
            "name": "Latin Beauty Academy",
            "city": "greenacres",
            "state": "FL",
            "zip": "33415-6104",
            "accreditor": "National Accrediting Commission of Career Arts and Sciences",
            "school_url": "www.latinbeautyacademy.edu/",
            "price_calculator_url": "www.latinbeautyacademy.edu/",
            "degrees_awarded": {
                "predominant_recoded": 1,
                "predominant": 1,
                "highest": 1
            },
            "under_investigation": 0,
            "main_campus": 1,
            "branches": 1,
            "ownership": 3,
            "state_fips": 12,
            "region_id": 5,
            "locale": 21,
            "degree_urbanization": null,
            "carnegie_basic": -2,
            "carnegie_undergrad": -2,
            "carnegie_size_setting": -2,
            "minority_serving": {
                "historically_black": 0,
                "predominantly_black": 0,
                "annh": 0,
                "tribal": 0,
                "aanipi": 0,
                "hispanic": 0,
                "nant": 0
            },
            "men_only": 0,
            "women_only": 0,
            "religious_affiliation": null,
            "online_only": 0,
            "operating": 1,
            "tuition_revenue_per_fte": 5180,
            "instructional_expenditure_per_fte": 2593,
            "faculty_salary": null,
            "ft_faculty_rate": null,
            "alias": null,
            "institutional_characteristics": {
                "level": 3
            },
            "open_admissions_policy": 1,
            "accreditor_code": "NACCAS",
            "title_iv": {
                "approval_date": "1/7/2015",
                "eligibility_type": 1
            },
            "ownership_peps": 3,
            "endowment": {
                "begin": null,
                "end": null
            },
            "dolflag": 0,
            "search": null
        },
        "id": 485485
    },
    {
        "school": {
            "name": "Associated Barber College of San Diego",
            "city": "San Diego",
            "state": "CA",
            "zip": "92101-4210",
            "accreditor": "National Accrediting Commission of Career Arts and Sciences",
            "school_url": "sandiegobarbercollege.com/",
            "price_calculator_url": "sandiegobarbercollege.com/calculator/",
            "degrees_awarded": {
                "predominant_recoded": 1,
                "predominant": 1,
                "highest": 1
            },
            "under_investigation": 0,
            "main_campus": 1,
            "branches": 1,
            "ownership": 3,
            "state_fips": 6,
            "region_id": 8,
            "locale": 11,
            "degree_urbanization": null,
            "carnegie_basic": -2,
            "carnegie_undergrad": -2,
            "carnegie_size_setting": -2,
            "minority_serving": {
                "historically_black": 0,
                "predominantly_black": 0,
                "annh": 0,
                "tribal": 0,
                "aanipi": 0,
                "hispanic": 0,
                "nant": 0
            },
            "men_only": 0,
            "women_only": 0,
            "religious_affiliation": null,
            "online_only": 0,
            "operating": 1,
            "tuition_revenue_per_fte": 7683,
            "instructional_expenditure_per_fte": 4083,
            "faculty_salary": null,
            "ft_faculty_rate": null,
            "alias": null,
            "institutional_characteristics": {
                "level": 3
            },
            "open_admissions_policy": 1,
            "accreditor_code": "NACCAS",
            "title_iv": {
                "approval_date": "5/15/2015",
                "eligibility_type": 1
            },
            "ownership_peps": 3,
            "endowment": {
                "begin": null,
                "end": null
            },
            "dolflag": 0,
            "search": null
        },
        "id": 485494
    },
    {
        "school": {
            "name": "ABCO Technology",
            "city": "Inglewood",
            "state": "CA",
            "zip": "90304-1551",
            "accreditor": "Accrediting Commission of Career Schools and Colleges",
            "school_url": "www.abcotechnology.edu/",
            "price_calculator_url": "www.abcotechnology.edu/disclosures/NPC",
            "degrees_awarded": {
                "predominant_recoded": 1,
                "predominant": 1,
                "highest": 1
            },
            "under_investigation": 0,
            "main_campus": 1,
            "branches": 1,
            "ownership": 3,
            "state_fips": 6,
            "region_id": 8,
            "locale": 21,
            "degree_urbanization": null,
            "carnegie_basic": -2,
            "carnegie_undergrad": -2,
            "carnegie_size_setting": -2,
            "minority_serving": {
                "historically_black": 0,
                "predominantly_black": 0,
                "annh": 0,
                "tribal": 0,
                "aanipi": 0,
                "hispanic": 0,
                "nant": 0
            },
            "men_only": 0,
            "women_only": 0,
            "religious_affiliation": null,
            "online_only": 0,
            "operating": 1,
            "tuition_revenue_per_fte": 19933,
            "instructional_expenditure_per_fte": 1985,
            "faculty_salary": null,
            "ft_faculty_rate": null,
            "alias": null,
            "institutional_characteristics": {
                "level": 3
            },
            "open_admissions_policy": 1,
            "accreditor_code": "ACCSC",
            "title_iv": {
                "approval_date": "5/15/2015",
                "eligibility_type": 1
            },
            "ownership_peps": 3,
            "endowment": {
                "begin": null,
                "end": null
            },
            "dolflag": 1,
            "search": null
        },
        "id": 485500
    },
    {
        "school": {
            "name": "Lionel University",
            "city": "Carpinteria",
            "state": "CA",
            "zip": "93013-2912",
            "accreditor": "Distance Education Accrediting Commission",
            "school_url": "lionel.edu/",
            "price_calculator_url": "lionel.edu/hubfs/net-price-caluculator.html?hsLang=en",
            "degrees_awarded": {
                "predominant_recoded": 2,
                "predominant": 2,
                "highest": 2
            },
            "under_investigation": 0,
            "main_campus": 1,
            "branches": 1,
            "ownership": 3,
            "state_fips": 6,
            "region_id": 8,
            "locale": 22,
            "degree_urbanization": null,
            "carnegie_basic": 13,
            "carnegie_undergrad": 1,
            "carnegie_size_setting": 1,
            "minority_serving": {
                "historically_black": 0,
                "predominantly_black": 0,
                "annh": 0,
                "tribal": 0,
                "aanipi": 0,
                "hispanic": 0,
                "nant": 0
            },
            "men_only": 0,
            "women_only": 0,
            "religious_affiliation": null,
            "online_only": 1,
            "operating": 1,
            "tuition_revenue_per_fte": 4498,
            "instructional_expenditure_per_fte": 1633,
            "faculty_salary": 3722,
            "ft_faculty_rate": null,
            "alias": "Lionel",
            "institutional_characteristics": {
                "level": 1
            },
            "open_admissions_policy": 1,
            "accreditor_code": "DETC",
            "title_iv": {
                "approval_date": "6/30/2015",
                "eligibility_type": 1
            },
            "ownership_peps": 3,
            "endowment": {
                "begin": null,
                "end": null
            },
            "dolflag": 0,
            "search": null
        },
        "id": 485519
    },
    {
        "school": {
            "name": "University of Texas Health Science Center at Tyler",
            "city": "Tyler",
            "state": "TX",
            "zip": "75708-3154",
            "accreditor": "Southern Association of Colleges and Schools Commission on Colleges",
            "school_url": "https://www.uthct.edu/",
            "price_calculator_url": "https://www.uth.edu/sfs/financial-aid/attendance.htm",
            "degrees_awarded": {
                "predominant_recoded": null,
                "predominant": 4,
                "highest": 4
            },
            "under_investigation": 0,
            "main_campus": 1,
            "branches": 1,
            "ownership": 1,
            "state_fips": 48,
            "region_id": 6,
            "locale": 12,
            "degree_urbanization": null,
            "carnegie_basic": 26,
            "carnegie_undergrad": 0,
            "carnegie_size_setting": 18,
            "minority_serving": {
                "historically_black": 0,
                "predominantly_black": 0,
                "annh": 0,
                "tribal": 0,
                "aanipi": 0,
                "hispanic": 0,
                "nant": 0
            },
            "men_only": 0,
            "women_only": 0,
            "religious_affiliation": null,
            "online_only": 0,
            "operating": 1,
            "tuition_revenue_per_fte": 5633,
            "instructional_expenditure_per_fte": 314766,
            "faculty_salary": 9184,
            "ft_faculty_rate": 0.9307,
            "alias": "UT Health",
            "institutional_characteristics": {
                "level": 1
            },
            "open_admissions_policy": null,
            "accreditor_code": "SACSCC",
            "title_iv": {
                "approval_date": "6/23/2015",
                "eligibility_type": 1
            },
            "ownership_peps": 1,
            "endowment": {
                "begin": 51814191,
                "end": 54325529
            },
            "dolflag": 0,
            "search": null
        },
        "id": 485537
    },
    {
        "school": {
            "name": "California Intercontinental University",
            "city": "Irvine",
            "state": "CA",
            "zip": "92614",
            "accreditor": "Distance Education Accrediting Commission",
            "school_url": "https://www.caluniversity.edu/",
            "price_calculator_url": "https://www.caluniversity.edu/netpricecalculator/",
            "degrees_awarded": {
                "predominant_recoded": 3,
                "predominant": 3,
                "highest": 4
            },
            "under_investigation": 0,
            "main_campus": 1,
            "branches": 1,
            "ownership": 3,
            "state_fips": 6,
            "region_id": 8,
            "locale": 11,
            "degree_urbanization": null,
            "carnegie_basic": 29,
            "carnegie_undergrad": 5,
            "carnegie_size_setting": 6,
            "minority_serving": {
                "historically_black": 0,
                "predominantly_black": 0,
                "annh": 0,
                "tribal": 0,
                "aanipi": 0,
                "hispanic": 0,
                "nant": 0
            },
            "men_only": 0,
            "women_only": 0,
            "religious_affiliation": null,
            "online_only": 1,
            "operating": 1,
            "tuition_revenue_per_fte": 10427,
            "instructional_expenditure_per_fte": 1884,
            "faculty_salary": 4167,
            "ft_faculty_rate": 0,
            "alias": null,
            "institutional_characteristics": {
                "level": 1
            },
            "open_admissions_policy": 1,
            "accreditor_code": "DETC",
            "title_iv": {
                "approval_date": "6/19/2015",
                "eligibility_type": 1
            },
            "ownership_peps": 3,
            "endowment": {
                "begin": null,
                "end": null
            },
            "dolflag": 0,
            "search": null
        },
        "id": 485546
    },
    {
        "school": {
            "name": "Infinity College",
            "city": "Lafayette",
            "state": "LA",
            "zip": "70501-8833",
            "accreditor": "Council on Occupational Education",
            "school_url": "www.infinitycollege.edu/",
            "price_calculator_url": "www.infinitycollege.edu/consumer-information.html",
            "degrees_awarded": {
                "predominant_recoded": 1,
                "predominant": 1,
                "highest": 1
            },
            "under_investigation": 0,
            "main_campus": 1,
            "branches": 1,
            "ownership": 3,
            "state_fips": 22,
            "region_id": 5,
            "locale": 12,
            "degree_urbanization": null,
            "carnegie_basic": -2,
            "carnegie_undergrad": -2,
            "carnegie_size_setting": -2,
            "minority_serving": {
                "historically_black": 0,
                "predominantly_black": 0,
                "annh": 0,
                "tribal": 0,
                "aanipi": 0,
                "hispanic": 0,
                "nant": 0
            },
            "men_only": 0,
            "women_only": 0,
            "religious_affiliation": null,
            "online_only": 0,
            "operating": 1,
            "tuition_revenue_per_fte": 7938,
            "instructional_expenditure_per_fte": 1463,
            "faculty_salary": null,
            "ft_faculty_rate": null,
            "alias": null,
            "institutional_characteristics": {
                "level": 3
            },
            "open_admissions_policy": 1,
            "accreditor_code": "COE",
            "title_iv": {
                "approval_date": "5/28/2015",
                "eligibility_type": 1
            },
            "ownership_peps": 3,
            "endowment": {
                "begin": null,
                "end": null
            },
            "dolflag": 1,
            "search": null
        },
        "id": 485564
    },
    {
        "school": {
            "name": "Universal Healthcare Careers College",
            "city": "Los Angeles",
            "state": "CA",
            "zip": "90015-3811",
            "accreditor": "Accrediting Commission of Career Schools and Colleges",
            "school_url": "www.uhcc.edu/",
            "price_calculator_url": "www.uhcc.edu/disclosures/",
            "degrees_awarded": {
                "predominant_recoded": 1,
                "predominant": 1,
                "highest": 1
            },
            "under_investigation": 0,
            "main_campus": 1,
            "branches": 1,
            "ownership": 3,
            "state_fips": 6,
            "region_id": 8,
            "locale": 11,
            "degree_urbanization": null,
            "carnegie_basic": -2,
            "carnegie_undergrad": -2,
            "carnegie_size_setting": -2,
            "minority_serving": {
                "historically_black": 0,
                "predominantly_black": 0,
                "annh": 0,
                "tribal": 0,
                "aanipi": 0,
                "hispanic": 0,
                "nant": 0
            },
            "men_only": 0,
            "women_only": 0,
            "religious_affiliation": null,
            "online_only": 0,
            "operating": 1,
            "tuition_revenue_per_fte": 9941,
            "instructional_expenditure_per_fte": 1652,
            "faculty_salary": null,
            "ft_faculty_rate": null,
            "alias": null,
            "institutional_characteristics": {
                "level": 3
            },
            "open_admissions_policy": 1,
            "accreditor_code": "ACCSC",
            "title_iv": {
                "approval_date": "4/23/2015",
                "eligibility_type": 1
            },
            "ownership_peps": 3,
            "endowment": {
                "begin": null,
                "end": null
            },
            "dolflag": 0,
            "search": null
        },
        "id": 485573
    },
    {
        "school": {
            "name": "MKG Beauty & Business",
            "city": "Cranston",
            "state": "RI",
            "zip": "02920-4358",
            "accreditor": null,
            "school_url": "www.mkgacademy.edu/",
            "price_calculator_url": "www.mkgacademy.edu/NetPriceCalculator/npcalc.htm",
            "degrees_awarded": {
                "predominant_recoded": 1,
                "predominant": 1,
                "highest": 1
            },
            "under_investigation": 0,
            "main_campus": 1,
            "branches": 1,
            "ownership": 3,
            "state_fips": 44,
            "region_id": 1,
            "locale": 21,
            "degree_urbanization": null,
            "carnegie_basic": -2,
            "carnegie_undergrad": -2,
            "carnegie_size_setting": -2,
            "minority_serving": {
                "historically_black": 0,
                "predominantly_black": 0,
                "annh": 0,
                "tribal": 0,
                "aanipi": 0,
                "hispanic": 0,
                "nant": 0
            },
            "men_only": 0,
            "women_only": 0,
            "religious_affiliation": null,
            "online_only": 0,
            "operating": 1,
            "tuition_revenue_per_fte": 15378,
            "instructional_expenditure_per_fte": 14516,
            "faculty_salary": null,
            "ft_faculty_rate": null,
            "alias": "Michael K. Galvin Beauty & Business Academy",
            "institutional_characteristics": {
                "level": 3
            },
            "open_admissions_policy": 1,
            "accreditor_code": null,
            "title_iv": {
                "approval_date": "12/18/2014",
                "eligibility_type": 7
            },
            "ownership_peps": null,
            "endowment": {
                "begin": null,
                "end": null
            },
            "dolflag": 1,
            "search": null
        },
        "id": 485582
    },
    {
        "school": {
            "name": "New Beginnings Beauty Academy",
            "city": "Pine Bluff",
            "state": "AR",
            "zip": "71603-5257",
            "accreditor": "National Accrediting Commission of Career Arts and Sciences",
            "school_url": "nbbacosmetology.com/",
            "price_calculator_url": "nbbacosmetology.com/",
            "degrees_awarded": {
                "predominant_recoded": 1,
                "predominant": 1,
                "highest": 1
            },
            "under_investigation": 0,
            "main_campus": 1,
            "branches": 1,
            "ownership": 3,
            "state_fips": 5,
            "region_id": 5,
            "locale": 13,
            "degree_urbanization": null,
            "carnegie_basic": -2,
            "carnegie_undergrad": -2,
            "carnegie_size_setting": -2,
            "minority_serving": {
                "historically_black": 0,
                "predominantly_black": 0,
                "annh": 0,
                "tribal": 0,
                "aanipi": 0,
                "hispanic": 0,
                "nant": 0
            },
            "men_only": 0,
            "women_only": 0,
            "religious_affiliation": null,
            "online_only": 0,
            "operating": 1,
            "tuition_revenue_per_fte": 8163,
            "instructional_expenditure_per_fte": 1089,
            "faculty_salary": null,
            "ft_faculty_rate": null,
            "alias": null,
            "institutional_characteristics": {
                "level": 3
            },
            "open_admissions_policy": 1,
            "accreditor_code": "NACCAS",
            "title_iv": {
                "approval_date": "6/1/2015",
                "eligibility_type": 1
            },
            "ownership_peps": 3,
            "endowment": {
                "begin": null,
                "end": null
            },
            "dolflag": 0,
            "search": null
        },
        "id": 485591
    },
    {
        "school": {
            "name": "Dolce The Academy",
            "city": "Waterbury",
            "state": "CT",
            "zip": "06705",
            "accreditor": "National Accrediting Commission of Career Arts and Sciences",
            "school_url": "www.dolceacademy.edu/",
            "price_calculator_url": "www.dolceacademy.edu/netpricecalculator",
            "degrees_awarded": {
                "predominant_recoded": 1,
                "predominant": 1,
                "highest": 1
            },
            "under_investigation": 0,
            "main_campus": 1,
            "branches": 1,
            "ownership": 3,
            "state_fips": 9,
            "region_id": 1,
            "locale": 22,
            "degree_urbanization": null,
            "carnegie_basic": -2,
            "carnegie_undergrad": -2,
            "carnegie_size_setting": -2,
            "minority_serving": {
                "historically_black": 0,
                "predominantly_black": 0,
                "annh": 0,
                "tribal": 0,
                "aanipi": 0,
                "hispanic": 0,
                "nant": 0
            },
            "men_only": 0,
            "women_only": 0,
            "religious_affiliation": null,
            "online_only": 0,
            "operating": 1,
            "tuition_revenue_per_fte": 5854,
            "instructional_expenditure_per_fte": 1726,
            "faculty_salary": null,
            "ft_faculty_rate": null,
            "alias": "Dolce Academy",
            "institutional_characteristics": {
                "level": 3
            },
            "open_admissions_policy": 1,
            "accreditor_code": "NACCAS",
            "title_iv": {
                "approval_date": "7/1/2015",
                "eligibility_type": 1
            },
            "ownership_peps": 3,
            "endowment": {
                "begin": null,
                "end": null
            },
            "dolflag": 0,
            "search": null
        },
        "id": 485607
    },
    {
        "school": {
            "name": "American College of the Building Arts",
            "city": "Charleston",
            "state": "SC",
            "zip": "29403-4223",
            "accreditor": "Accrediting Commission of Career Schools and Colleges",
            "school_url": "acba.edu/",
            "price_calculator_url": "acba.edu/NetPrice",
            "degrees_awarded": {
                "predominant_recoded": null,
                "predominant": 3,
                "highest": 3
            },
            "under_investigation": 0,
            "main_campus": 1,
            "branches": 1,
            "ownership": 2,
            "state_fips": 45,
            "region_id": 5,
            "locale": 12,
            "degree_urbanization": null,
            "carnegie_basic": -2,
            "carnegie_undergrad": -2,
            "carnegie_size_setting": -2,
            "minority_serving": {
                "historically_black": 0,
                "predominantly_black": 0,
                "annh": 0,
                "tribal": 0,
                "aanipi": 0,
                "hispanic": 0,
                "nant": 0
            },
            "men_only": 0,
            "women_only": 0,
            "religious_affiliation": null,
            "online_only": 0,
            "operating": 1,
            "tuition_revenue_per_fte": 14329,
            "instructional_expenditure_per_fte": 15652,
            "faculty_salary": 5811,
            "ft_faculty_rate": 0.5833,
            "alias": null,
            "institutional_characteristics": {
                "level": 1
            },
            "open_admissions_policy": 2,
            "accreditor_code": "ACCSC",
            "title_iv": {
                "approval_date": "4/19/2019",
                "eligibility_type": 1
            },
            "ownership_peps": 2,
            "endowment": {
                "begin": 624372,
                "end": 699023
            },
            "dolflag": 1,
            "search": null
        },
        "id": 485698
    },
    {
        "school": {
            "name": "River Valley School of Massage",
            "city": "Russellville",
            "state": "AR",
            "zip": "72802",
            "accreditor": "Accrediting Commission of Career Schools and Colleges",
            "school_url": "https://www.rvsmassage.com/",
            "price_calculator_url": "https://rvsmassage.com/wp-content/uploads/2018/07/npcalc-1.htm",
            "degrees_awarded": {
                "predominant_recoded": 1,
                "predominant": 1,
                "highest": 1
            },
            "under_investigation": 0,
            "main_campus": 1,
            "branches": 1,
            "ownership": 3,
            "state_fips": 5,
            "region_id": 5,
            "locale": 33,
            "degree_urbanization": null,
            "carnegie_basic": -2,
            "carnegie_undergrad": -2,
            "carnegie_size_setting": -2,
            "minority_serving": {
                "historically_black": 0,
                "predominantly_black": 0,
                "annh": 0,
                "tribal": 0,
                "aanipi": 0,
                "hispanic": 0,
                "nant": 0
            },
            "men_only": 0,
            "women_only": 0,
            "religious_affiliation": null,
            "online_only": 0,
            "operating": 1,
            "tuition_revenue_per_fte": 7900,
            "instructional_expenditure_per_fte": 3289,
            "faculty_salary": null,
            "ft_faculty_rate": null,
            "alias": "RVSM",
            "institutional_characteristics": {
                "level": 3
            },
            "open_admissions_policy": 1,
            "accreditor_code": "ACCSC",
            "title_iv": {
                "approval_date": "7/29/2015",
                "eligibility_type": 1
            },
            "ownership_peps": 3,
            "endowment": {
                "begin": null,
                "end": null
            },
            "dolflag": 0,
            "search": null
        },
        "id": 485704
    },
    {
        "school": {
            "name": "Atlantis University",
            "city": "Miami",
            "state": "FL",
            "zip": "33132",
            "accreditor": "Accrediting Commission of Career Schools and Colleges",
            "school_url": "www.atlantisuniversity.edu/",
            "price_calculator_url": "new.atlantisuniversity.edu/wp-content/uploads/2019/11/net-price-calculator.html",
            "degrees_awarded": {
                "predominant_recoded": 2,
                "predominant": 3,
                "highest": 4
            },
            "under_investigation": 0,
            "main_campus": 1,
            "branches": 1,
            "ownership": 3,
            "state_fips": 12,
            "region_id": 5,
            "locale": 11,
            "degree_urbanization": null,
            "carnegie_basic": 22,
            "carnegie_undergrad": 10,
            "carnegie_size_setting": 6,
            "minority_serving": {
                "historically_black": 0,
                "predominantly_black": 0,
                "annh": 0,
                "tribal": 0,
                "aanipi": 0,
                "hispanic": 0,
                "nant": 0
            },
            "men_only": 0,
            "women_only": 0,
            "religious_affiliation": null,
            "online_only": 0,
            "operating": 1,
            "tuition_revenue_per_fte": 55212,
            "instructional_expenditure_per_fte": 15036,
            "faculty_salary": 4333,
            "ft_faculty_rate": 0.4681,
            "alias": null,
            "institutional_characteristics": {
                "level": 1
            },
            "open_admissions_policy": 1,
            "accreditor_code": "ACCSC",
            "title_iv": {
                "approval_date": "8/21/2014",
                "eligibility_type": 1
            },
            "ownership_peps": 3,
            "endowment": {
                "begin": null,
                "end": null
            },
            "dolflag": 0,
            "search": null
        },
        "id": 485768
    },
    {
        "school": {
            "name": "Westchester School for Medical & Dental Assistants",
            "city": "Ardsley",
            "state": "NY",
            "zip": "10502",
            "accreditor": "Accrediting Council for Continuing Education & Training",
            "school_url": "dentaltrainingwp.com/",
            "price_calculator_url": "www.dentaltrainingwp.com/",
            "degrees_awarded": {
                "predominant_recoded": 1,
                "predominant": 1,
                "highest": 1
            },
            "under_investigation": 0,
            "main_campus": 1,
            "branches": 1,
            "ownership": 3,
            "state_fips": 36,
            "region_id": 2,
            "locale": 21,
            "degree_urbanization": null,
            "carnegie_basic": -2,
            "carnegie_undergrad": -2,
            "carnegie_size_setting": -2,
            "minority_serving": {
                "historically_black": 0,
                "predominantly_black": 0,
                "annh": 0,
                "tribal": 0,
                "aanipi": 0,
                "hispanic": 0,
                "nant": 0
            },
            "men_only": 0,
            "women_only": 0,
            "religious_affiliation": null,
            "online_only": 0,
            "operating": 1,
            "tuition_revenue_per_fte": 4452,
            "instructional_expenditure_per_fte": 3209,
            "faculty_salary": null,
            "ft_faculty_rate": null,
            "alias": null,
            "institutional_characteristics": {
                "level": 3
            },
            "open_admissions_policy": 1,
            "accreditor_code": "ACCET",
            "title_iv": {
                "approval_date": "6/19/2014",
                "eligibility_type": 1
            },
            "ownership_peps": 3,
            "endowment": {
                "begin": null,
                "end": null
            },
            "dolflag": 1,
            "search": null
        },
        "id": 485801
    },
    {
        "school": {
            "name": "K & G 5 Star Barber College",
            "city": "League City",
            "state": "TX",
            "zip": "77573",
            "accreditor": null,
            "school_url": "www.kandgbarbercollege.com/",
            "price_calculator_url": "www.kandgbarbercollege.com/net-price-calculator.html",
            "degrees_awarded": {
                "predominant_recoded": 1,
                "predominant": 1,
                "highest": 1
            },
            "under_investigation": 0,
            "main_campus": 1,
            "branches": 1,
            "ownership": 3,
            "state_fips": 48,
            "region_id": 6,
            "locale": 22,
            "degree_urbanization": null,
            "carnegie_basic": -2,
            "carnegie_undergrad": -2,
            "carnegie_size_setting": -2,
            "minority_serving": {
                "historically_black": 0,
                "predominantly_black": 0,
                "annh": 0,
                "tribal": 0,
                "aanipi": 0,
                "hispanic": 0,
                "nant": 0
            },
            "men_only": 0,
            "women_only": 0,
            "religious_affiliation": null,
            "online_only": 0,
            "operating": 0,
            "tuition_revenue_per_fte": 17140,
            "instructional_expenditure_per_fte": 1083,
            "faculty_salary": null,
            "ft_faculty_rate": null,
            "alias": null,
            "institutional_characteristics": {
                "level": 3
            },
            "open_admissions_policy": 1,
            "accreditor_code": null,
            "title_iv": {
                "approval_date": "6/19/2014",
                "eligibility_type": 1
            },
            "ownership_peps": null,
            "endowment": {
                "begin": null,
                "end": null
            },
            "dolflag": 0,
            "search": null
        },
        "id": 485810
    }
]